pysistency/__init__.py
pysistency/meta.py
pysistency/pdict.py
pysistency/plist.py
pysistency/backend/__init__.py
pysistency/backend/base_store.py
pysistency/backend/file_store.py
pysistency/utilities/__init__.py
pysistency/utilities/constants.py
pysistency/utilities/exceptions.py
pysistency/utilities/keys.py
pysistency/utilities/std_clone.py
pysistency-0.1.0.dist-info/DESCRIPTION.rst
pysistency-0.1.0.dist-info/METADATA
pysistency-0.1.0.dist-info/RECORD
pysistency-0.1.0.dist-info/WHEEL
pysistency-0.1.0.dist-info/metadata.json
pysistency-0.1.0.dist-info/top_level.txt
