Metadata-Version: 2.0
Name: pysistency
Version: 0.1.0
Summary: Python containers with persistency
Home-page: https://github.com/maxfischer2781/pysistency
Author: Max Fischer
Author-email: maxfischer2781@gmail.com
License: Apache V2.0
Keywords: container persistent
Platform: Operating System :: OS Independent
Classifier: Development Status :: 4 - Beta
Classifier: Intended Audience :: Developers
Classifier: License :: OSI Approved :: Apache Software License
Classifier: Programming Language :: Python :: 3.4
Classifier: Programming Language :: Python :: 3.5
Classifier: Programming Language :: Python :: Implementation :: CPython
Classifier: Topic :: Software Development
Classifier: Topic :: Software Development :: Libraries :: Python Modules
Classifier: Topic :: Utilities
